{
  "annotations": {
    "list": [
      {
        "builtIn": 1,
        "datasource": "-- Grafana --",
        "enable": true,
        "hide": true,
        "iconColor": "rgba(0, 211, 255, 1)",
        "name": "Annotations & Alerts",
        "type": "dashboard"
      }
    ]
  },
  "editable": true,
  "gnetId": null,
  "graphTooltip": 0,
  "id": null,
  "links": [],
  "panels": [
    {
      "datasource": "Prometheus",
      "fieldConfig": {
        "defaults": {
          "color": {
            "mode": "thresholds"
          },
          "mappings": [],
          "thresholds": {
            "mode": "absolute",
            "steps": [
              {
                "color": "green",
                "value": null
              }
            ]
          },
          "unit": "short"
        }
      },
      "gridPos": {
        "h": 5,
        "w": 4,
        "x": 0,
        "y": 0
      },
      "id": 1,
      "options": {
        "reduceOptions": {
          "calcs": ["lastNotNull"],
          "fields": "",
          "values": false
        },
        "orientation": "auto",
        "text": {},
        "textMode": "auto",
        "colorMode": "value",
        "graphMode": "area"
      },
      "pluginVersion": "8.0.0",
      "targets": [
        {
          "expr": "count(count by (device_id) (rate(iot_monitoring_sensor_readings_total[1m])))",
          "refId": "A"
        }
      ],
      "title": "Active Devices",
      "type": "stat"
    },
    {
      "datasource": "Prometheus",
      "fieldConfig": {
        "defaults": {
          "color": {
            "mode": "thresholds"
          },
          "mappings": [],
          "thresholds": {
            "mode": "absolute",
            "steps": [
              {
                "color": "green",
                "value": null
              }
            ]
          },
          "unit": "short"
        }
      },
      "gridPos": {
        "h": 5,
        "w": 4,
        "x": 4,
        "y": 0
      },
      "id": 2,
      "options": {
        "reduceOptions": {
          "calcs": ["lastNotNull"],
          "fields": "",
          "values": false
        },
        "orientation": "auto",
        "text": {},
        "textMode": "auto",
        "colorMode": "value",
        "graphMode": "area"
      },
      "pluginVersion": "8.0.0",
      "targets": [
        {
          "expr": "count(count by (sensor_id) (rate(iot_monitoring_sensor_readings_total[1m])))",
          "refId": "A"
        }
      ],
      "title": "Active Sensors",
      "type": "stat"
    },
    {
      "datasource": "Prometheus",
      "fieldConfig": {
        "defaults": {
          "color": {
            "mode": "thresholds"
          },
          "mappings": [],
          "thresholds": {
            "mode": "absolute",
            "steps": [
              {
                "color": "green",
                "value": null
              },
              {
                "color": "yellow",
                "value": 5
              },
              {
                "color": "red",
                "value": 20
              }
            ]
          },
          "unit": "short"
        }
      },
      "gridPos": {
        "h": 5,
        "w": 4,
        "x": 8,
        "y": 0
      },
      "id": 3,
      "options": {
        "reduceOptions": {
          "calcs": ["lastNotNull"],
          "fields": "",
          "values": false
        },
        "orientation": "auto",
        "text": {},
        "textMode": "auto",
        "colorMode": "background",
        "graphMode": "area"
      },
      "pluginVersion": "8.0.0",
      "targets": [
        {
          "expr": "sum(rate(iot_monitoring_alerts_total{severity=~\"warning|critical\"}[1m]))",
          "refId": "A"
        }
      ],
      "title": "Active Alerts",
      "type": "stat"
    },
    {
      "datasource": "Prometheus",
      "fieldConfig": {
        "defaults": {
          "color": {
            "mode": "thresholds"
          },
          "mappings": [],
          "thresholds": {
            "mode": "absolute",
            "steps": [
              {
                "color": "green",
                "value": null
              },
              {
                "color": "yellow",
                "value": 3
              },
              {
                "color": "red",
                "value": 10
              }
            ]
          },
          "unit": "short"
        }
      },
      "gridPos": {
        "h": 5,
        "w": 4,
        "x": 12,
        "y": 0
      },
      "id": 4,
      "options": {
        "reduceOptions": {
          "calcs": ["lastNotNull"],
          "fields": "",
          "values": false
        },
        "orientation": "auto",
        "text": {},
        "textMode": "auto",
        "colorMode": "background",
        "graphMode": "area"
      },
      "pluginVersion": "8.0.0",
      "targets": [
        {
          "expr": "sum(iot_monitoring_maintenance_required_total{priority=\"high\"})",
          "refId": "A"
        }
      ],
      "title": "Maintenance Required",
      "type": "stat"
    },
    {
      "datasource": "TimescaleDB",
      "fieldConfig": {
        "defaults": {
          "color": {
            "mode": "palette-classic"
          },
          "custom": {
            "axisLabel": "",
            "axisPlacement": "auto",
            "barAlignment": 0,
            "drawStyle": "line",
            "fillOpacity": 10,
            "gradientMode": "none",
            "hideFrom": {
              "tooltip": false,
              "viz": false,
              "legend": false
            },
            "lineInterpolation": "linear",
            "lineWidth": 1,
            "pointSize": 5,
            "scaleDistribution": {
              "type": "linear"
            },
            "showPoints": "never",
            "spanNulls": true
          },
          "mappings": [],
          "thresholds": {
            "mode": "absolute",
            "steps": [
              {
                "color": "green",
                "value": null
              },
              {
                "color": "red",
                "value": 80
              }
            ]
          },
          "unit": "celsius"
        }
      },
      "gridPos": {
        "h": 8,
        "w": 12,
        "x": 0,
        "y": 5
      },
      "id": 5,
      "options": {
        "legend": {
          "calcs": ["mean", "max", "last"],
          "displayMode": "table",
          "placement": "bottom"
        },
        "tooltip": {
          "mode": "multi"
        }
      },
      "targets": [
        {
          "format": "time_series",
          "rawSql": "SELECT time, AVG((value->>'average')::float) as avg_temp FROM sensor_aggregates WHERE $__timeFilter(time) AND value->>'sensor_type' = 'temperature' GROUP BY time ORDER BY time",
          "refId": "A"
        }
      ],
      "title": "Temperature Trends",
      "type": "timeseries"
    },
    {
      "datasource": "TimescaleDB",
      "fieldConfig": {
        "defaults": {
          "color": {
            "mode": "palette-classic"
          },
          "custom": {
            "axisLabel": "",
            "axisPlacement": "auto",
            "barAlignment": 0,
            "drawStyle": "line",
            "fillOpacity": 10,
            "gradientMode": "none",
            "hideFrom": {
              "tooltip": false,
              "viz": false,
              "legend": false
            },
            "lineInterpolation": "linear",
            "lineWidth": 1,
            "pointSize": 5,
            "scaleDistribution": {
              "type": "linear"
            },
            "showPoints": "never",
            "spanNulls": true
          },
          "mappings": [],
          "thresholds": {
            "mode": "absolute",
            "steps": [
              {
                "color": "green",
                "value": null
              },
              {
                "color": "red",
                "value": 150
              }
            ]
          },
          "unit": "psi"
        }
      },
      "gridPos": {
        "h": 8,
        "w": 12,
        "x": 12,
        "y": 5
      },
      "id": 6,
      "options": {
        "legend": {
          "calcs": ["mean", "max", "last"],
          "displayMode": "table",
          "placement": "bottom"
        },
        "tooltip": {
          "mode": "multi"
        }
      },
      "targets": [
        {
          "format": "time_series",
          "rawSql": "SELECT time, AVG((value->>'average')::float) as avg_pressure FROM sensor_aggregates WHERE $__timeFilter(time) AND value->>'sensor_type' = 'pressure' GROUP BY time ORDER BY time",
          "refId": "A"
        }
      ],
      "title": "Pressure Trends",
      "type": "timeseries"
    },
    {
      "datasource": "TimescaleDB",
      "fieldConfig": {
        "defaults": {
          "color": {
            "mode": "palette-classic"
          },
          "custom": {
            "axisLabel": "",
            "axisPlacement": "auto",
            "barAlignment": 0,
            "drawStyle": "line",
            "fillOpacity": 20,
            "gradientMode": "opacity",
            "hideFrom": {
              "tooltip": false,
              "viz": false,
              "legend": false
            },
            "lineInterpolation": "smooth",
            "lineWidth": 2,
            "pointSize": 5,
            "scaleDistribution": {
              "type": "linear"
            },
            "showPoints": "never",
            "spanNulls": true
          },
          "mappings": [],
          "max": 100,
          "min": 0,
          "thresholds": {
            "mode": "absolute",
            "steps": [
              {
                "color": "red",
                "value": null
              },
              {
                "color": "orange",
                "value": 50
              },
              {
                "color": "yellow",
                "value": 75
              },
              {
                "color": "green",
                "value": 90
              }
            ]
          },
          "unit": "percent"
        }
      },
      "gridPos": {
        "h": 8,
        "w": 12,
        "x": 0,
        "y": 13
      },
      "id": 7,
      "options": {
        "legend": {
          "calcs": ["mean", "min"],
          "displayMode": "table",
          "placement": "bottom"
        },
        "tooltip": {
          "mode": "multi"
        }
      },
      "targets": [
        {
          "format": "time_series",
          "rawSql": "SELECT time, value->>'device_id' as device, (value->>'health_score')::float as health_score FROM maintenance_schedule WHERE $__timeFilter(time) GROUP BY time, device, health_score ORDER BY time",
          "refId": "A"
        }
      ],
      "title": "Device Health Scores",
      "type": "timeseries"
    },
    {
      "datasource": "TimescaleDB",
      "fieldConfig": {
        "defaults": {
          "color": {
            "mode": "thresholds"
          },
          "custom": {
            "align": "auto",
            "displayMode": "auto"
          },
          "mappings": [],
          "thresholds": {
            "mode": "absolute",
            "steps": [
              {
                "color": "green",
                "value": null
              },
              {
                "color": "yellow",
                "value": 30
              },
              {
                "color": "red",
                "value": 7
              }
            ]
          }
        }
      },
      "gridPos": {
        "h": 8,
        "w": 12,
        "x": 12,
        "y": 13
      },
      "id": 8,
      "options": {
        "showHeader": true,
        "sortBy": [
          {
            "desc": false,
            "displayName": "Days to Failure"
          }
        ]
      },
      "pluginVersion": "8.0.0",
      "targets": [
        {
          "format": "table",
          "rawSql": "SELECT value->'prediction'->>'device_id' as \"Device ID\", value->'prediction'->>'sensor_id' as \"Sensor ID\", value->'prediction'->>'priority' as \"Priority\", (value->'prediction'->>'estimated_days_to_failure')::int as \"Days to Failure\", ROUND((value->'prediction'->>'health_score')::numeric, 1) as \"Health %\", value->'prediction'->>'reason' as \"Reason\" FROM maintenance_schedule WHERE time > NOW() - INTERVAL '1 hour' AND (value->'prediction'->>'requires_maintenance')::boolean = true ORDER BY (value->'prediction'->>'estimated_days_to_failure')::int ASC LIMIT 20",
          "refId": "A"
        }
      ],
      "title": "Maintenance Schedule",
      "type": "table"
    },
    {
      "datasource": "TimescaleDB",
      "fieldConfig": {
        "defaults": {
          "color": {
            "mode": "palette-classic"
          },
          "custom": {
            "hideFrom": {
              "tooltip": false,
              "viz": false,
              "legend": false
            }
          },
          "mappings": []
        }
      },
      "gridPos": {
        "h": 7,
        "w": 8,
        "x": 0,
        "y": 21
      },
      "id": 9,
      "options": {
        "legend": {
          "calcs": ["sum"],
          "displayMode": "table",
          "placement": "right",
          "values": ["value"]
        },
        "pieType": "pie",
        "tooltip": {
          "mode": "single"
        }
      },
      "targets": [
        {
          "format": "table",
          "rawSql": "SELECT value->>'severity' as severity, COUNT(*) as count FROM sensor_alerts WHERE time > NOW() - INTERVAL '1 hour' GROUP BY severity",
          "refId": "A"
        }
      ],
      "title": "Alerts by Severity",
      "type": "piechart"
    },
    {
      "datasource": "TimescaleDB",
      "fieldConfig": {
        "defaults": {
          "color": {
            "mode": "palette-classic"
          },
          "custom": {
            "axisLabel": "Count",
            "axisPlacement": "auto",
            "fillOpacity": 80,
            "gradientMode": "none",
            "hideFrom": {
              "tooltip": false,
              "viz": false,
              "legend": false
            },
            "lineWidth": 1
          },
          "mappings": [],
          "thresholds": {
            "mode": "absolute",
            "steps": [
              {
                "color": "green",
                "value": null
              }
            ]
          }
        }
      },
      "gridPos": {
        "h": 7,
        "w": 8,
        "x": 8,
        "y": 21
      },
      "id": 10,
      "options": {
        "legend": {
          "calcs": [],
          "displayMode": "list",
          "placement": "bottom"
        },
        "orientation": "horizontal",
        "tooltip": {
          "mode": "single"
        }
      },
      "targets": [
        {
          "format": "table",
          "rawSql": "SELECT value->>'location' as location, COUNT(*) as count FROM sensor_aggregates WHERE time > NOW() - INTERVAL '1 hour' GROUP BY location ORDER BY count DESC LIMIT 10",
          "refId": "A"
        }
      ],
      "title": "Sensor Activity by Location",
      "type": "barchart"
    },
    {
      "datasource": "TimescaleDB",
      "fieldConfig": {
        "defaults": {
          "color": {
            "mode": "palette-classic"
          },
          "custom": {
            "axisLabel": "",
            "axisPlacement": "auto",
            "barAlignment": 0,
            "drawStyle": "line",
            "fillOpacity": 10,
            "gradientMode": "none",
            "hideFrom": {
              "tooltip": false,
              "viz": false,
              "legend": false
            },
            "lineInterpolation": "linear",
            "lineWidth": 1,
            "pointSize": 5,
            "scaleDistribution": {
              "type": "linear"
            },
            "showPoints": "never",
            "spanNulls": true
          },
          "mappings": [],
          "thresholds": {
            "mode": "absolute",
            "steps": [
              {
                "color": "green",
                "value": null
              }
            ]
          },
          "unit": "hz"
        }
      },
      "gridPos": {
        "h": 7,
        "w": 8,
        "x": 16,
        "y": 21
      },
      "id": 11,
      "options": {
        "legend": {
          "calcs": ["mean", "max"],
          "displayMode": "table",
          "placement": "bottom"
        },
        "tooltip": {
          "mode": "multi"
        }
      },
      "targets": [
        {
          "format": "time_series",
          "rawSql": "SELECT time, AVG((value->>'average')::float) as avg_vibration FROM sensor_aggregates WHERE $__timeFilter(time) AND value->>'sensor_type' = 'vibration' GROUP BY time ORDER BY time",
          "refId": "A"
        }
      ],
      "title": "Vibration Levels",
      "type": "timeseries"
    }
  ],
  "refresh": "10s",
  "schemaVersion": 27,
  "style": "dark",
  "tags": ["iot", "sensors", "monitoring", "maintenance"],
  "templating": {
    "list": []
  },
  "time": {
    "from": "now-1h",
    "to": "now"
  },
  "timepicker": {},
  "timezone": "",
  "title": "IoT Sensor Monitoring Dashboard",
  "uid": "iot-monitoring",
  "version": 1
}
